<?xml version="1.0" encoding="UTF-8"?>
<tour start="node16" apprev="20025" appversion="7.0.10">
  <panorama hideabout="1" id="node16">
    <input height="2000" levelingpitch="0" width="2000" leveltilesize="510" levelbiashidpi="1.000" levelingroll="0" levelbias="0.400" overlap="1" leveltileurl="tiles/node16/cf_%c/l_%l/c_%x/tile_%y.jpg">
      <level predecode="0" width="2000" height="2000" preload="0"/>
      <level predecode="0" width="1000" height="1000" preload="0"/>
      <level predecode="1" width="500" height="500" preload="1"/>
      <preview strip="1" color="0x808080"/>
    </input>
    <view pannorth="0" fovmode="2">
      <start projection="4" fov="140.418" pan="-3.15743" tilt="-2.92085"/>
      <flyin projection="9" fov="170" pan="0" tilt="-90"/>
      <min fovpixel="2" pan="0" tilt="-90"/>
      <max fovfisheye="360" scaletofit="1" fovstereographic="330" fov="140" pan="360" tilt="90"/>
    </view>
    <userdata nodeid="node16" datetime="2024:10:12 09:45:54" latitude="37.328506" heading="0" title="세대입구" tags="101동 901호 VR" customnodeid="" comment="" author="" info="" source="" copyright="" longitude="127.129253" description="" altitude="139.57"/>
    <hotspots smoothmovement="0" width="180" height="20" wordwrap="1">
      <label textalpha="1" borderradius="1" height="20" textcolor="0x000000" wordwrap="1" width="180" enabled="1" backgroundcolor="0xffffff" borderalpha="1" background="1" backgroundalpha="1" bordercolor="0x000000" border="1"/>
      <polystyle backgroundcolor="0x0000ff" borderalpha="1" handcursor="1" backgroundalpha="0.25098" mode="0" bordercolor="0x0000ff"/>
      <hotspot tilt="-20.84" url="{node15}" skinid="ht_node" title="현관" pan="-353.61" description="" target="" id="Point01"/>
    </hotspots>
    <media/>
    <transition zoomout="0" zoomin="0" blendcolor="0x000000" type="crossdissolve" zoomafterinfov="140" zoomspeed="2" blendtime="1" delay="none" enabled="1" softedge="0" zoomoutpause="1" zoomfov="40" zoomafteroutfov="40"/>
    <autorotate speed="0.020" useanimation="0" nodedelay="0.00" nodefilter="" startloaded="0" horizonfromdefview="0" noderandom="1" delay="10.00" enabled="1" returntohorizon="0.000"/>
    <animation syncanimationwithvideo="0" clipsrandom="0" animsequence="Animation01" useinautorotation="0"/>
    <control invertcontrol="1" lockedmouse="0" sensitivity="8" rubberband="0" lockedkeyboard="0" dblclickfullscreen="0" zoomcentercursor="1" contextfullscreen="1" contextprojections="0" lockedkeyboardzoom="0" invertwheel="0" speedwheel="1" contextvr="1" lockedwheel="0" simulatemass="1" hideabout="1"/>
  </panorama>
  <panorama hideabout="1" id="node15">
    <input height="2000" levelingpitch="0" width="2000" leveltilesize="510" levelbiashidpi="1.000" levelingroll="0" levelbias="0.400" overlap="1" leveltileurl="tiles/node15/cf_%c/l_%l/c_%x/tile_%y.jpg">
      <level predecode="0" width="2000" height="2000" preload="0"/>
      <level predecode="0" width="1000" height="1000" preload="0"/>
      <level predecode="1" width="500" height="500" preload="1"/>
      <preview strip="1" color="0x808080"/>
    </input>
    <view pannorth="0" fovmode="2">
      <start projection="4" fov="140.418" pan="170.562" tilt="-1.26678"/>
      <flyin projection="9" fov="170" pan="0" tilt="-90"/>
      <min fovpixel="2" pan="0" tilt="-90"/>
      <max fovfisheye="360" scaletofit="1" fovstereographic="330" fov="140" pan="360" tilt="90"/>
    </view>
    <userdata nodeid="node15" datetime="2024:10:12 09:45:50" latitude="37.328506" heading="0" title="현관" tags="101동 901호 VR" customnodeid="" comment="" author="" info="" source="" copyright="" longitude="127.129253" description="" altitude="139.57"/>
    <hotspots smoothmovement="0" width="180" height="20" wordwrap="1">
      <label textalpha="1" borderradius="1" height="20" textcolor="0x000000" wordwrap="1" width="180" enabled="1" backgroundcolor="0xffffff" borderalpha="1" background="1" backgroundalpha="1" bordercolor="0x000000" border="1"/>
      <polystyle backgroundcolor="0x0000ff" borderalpha="1" handcursor="1" backgroundalpha="0.25098" mode="0" bordercolor="0x0000ff"/>
      <hotspot tilt="-29.87" url="{node16}" skinid="ht_node" title="세대입구" pan="-9.12" description="" target="" id="Point01"/>
      <hotspot tilt="-39.12" url="{node14}" skinid="ht_node" title="현관창고" pan="-119.85" description="" target="" id="Point02"/>
      <hotspot tilt="-36.45" url="{node11}" skinid="ht_node" title="복도2" pan="-187.9" description="" target="" id="Point03"/>
    </hotspots>
    <media/>
    <transition zoomout="0" zoomin="0" blendcolor="0x000000" type="crossdissolve" zoomafterinfov="140" zoomspeed="2" blendtime="1" delay="none" enabled="1" softedge="0" zoomoutpause="1" zoomfov="40" zoomafteroutfov="40"/>
    <autorotate speed="0.020" useanimation="0" nodedelay="0.00" nodefilter="" startloaded="0" horizonfromdefview="0" noderandom="1" delay="10.00" enabled="1" returntohorizon="0.000"/>
    <animation syncanimationwithvideo="0" clipsrandom="0" animsequence="Animation01" useinautorotation="0"/>
    <control invertcontrol="1" lockedmouse="0" sensitivity="8" rubberband="0" lockedkeyboard="0" dblclickfullscreen="0" zoomcentercursor="1" contextfullscreen="1" contextprojections="0" lockedkeyboardzoom="0" invertwheel="0" speedwheel="1" contextvr="1" lockedwheel="0" simulatemass="1" hideabout="1"/>
  </panorama>
  <panorama hideabout="1" id="node14">
    <input height="2000" levelingpitch="0" width="2000" leveltilesize="510" levelbiashidpi="1.000" levelingroll="0" levelbias="0.400" overlap="1" leveltileurl="tiles/node14/cf_%c/l_%l/c_%x/tile_%y.jpg">
      <level predecode="0" width="2000" height="2000" preload="0"/>
      <level predecode="0" width="1000" height="1000" preload="0"/>
      <level predecode="1" width="500" height="500" preload="1"/>
      <preview strip="1" color="0x808080"/>
    </input>
    <view pannorth="0" fovmode="2">
      <start projection="4" fov="140.418" pan="177.793" tilt="-1.23534"/>
      <flyin projection="9" fov="170" pan="0" tilt="-90"/>
      <min fovpixel="2" pan="0" tilt="-90"/>
      <max fovfisheye="360" scaletofit="1" fovstereographic="330" fov="140" pan="360" tilt="90"/>
    </view>
    <userdata nodeid="node14" datetime="2024:10:12 09:45:44" latitude="37.328506" heading="0" title="현관창고" tags="101동 901호 VR" customnodeid="" comment="" author="" info="" source="" copyright="" longitude="127.129253" description="" altitude="139.57"/>
    <hotspots smoothmovement="0" width="180" height="20" wordwrap="1">
      <label textalpha="1" borderradius="1" height="20" textcolor="0x000000" wordwrap="1" width="180" enabled="1" backgroundcolor="0xffffff" borderalpha="1" background="1" backgroundalpha="1" bordercolor="0x000000" border="1"/>
      <polystyle backgroundcolor="0x0000ff" borderalpha="1" handcursor="1" backgroundalpha="0.25098" mode="0" bordercolor="0x0000ff"/>
      <hotspot tilt="-31.13" url="{node15}" skinid="ht_node" title="현관" pan="-178.62" description="" target="" id="Point01"/>
      <hotspot tilt="-29.34" url="{node13}" skinid="ht_node" title="실외기실" pan="-252.61" description="" target="" id="Point02"/>
    </hotspots>
    <media/>
    <transition zoomout="0" zoomin="0" blendcolor="0x000000" type="crossdissolve" zoomafterinfov="140" zoomspeed="2" blendtime="1" delay="none" enabled="1" softedge="0" zoomoutpause="1" zoomfov="40" zoomafteroutfov="40"/>
    <autorotate speed="0.020" useanimation="0" nodedelay="0.00" nodefilter="" startloaded="0" horizonfromdefview="0" noderandom="1" delay="10.00" enabled="1" returntohorizon="0.000"/>
    <animation syncanimationwithvideo="0" clipsrandom="0" animsequence="Animation01" useinautorotation="0"/>
    <control invertcontrol="1" lockedmouse="0" sensitivity="8" rubberband="0" lockedkeyboard="0" dblclickfullscreen="0" zoomcentercursor="1" contextfullscreen="1" contextprojections="0" lockedkeyboardzoom="0" invertwheel="0" speedwheel="1" contextvr="1" lockedwheel="0" simulatemass="1" hideabout="1"/>
  </panorama>
  <panorama hideabout="1" id="node13">
    <input height="2000" levelingpitch="0" width="2000" leveltilesize="510" levelbiashidpi="1.000" levelingroll="0" levelbias="0.400" overlap="1" leveltileurl="tiles/node13/cf_%c/l_%l/c_%x/tile_%y.jpg">
      <level predecode="0" width="2000" height="2000" preload="0"/>
      <level predecode="0" width="1000" height="1000" preload="0"/>
      <level predecode="1" width="500" height="500" preload="1"/>
      <preview strip="1" color="0x808080"/>
    </input>
    <view pannorth="0" fovmode="2">
      <start projection="4" fov="140.418" pan="179.041" tilt="-1.23534"/>
      <flyin projection="9" fov="170" pan="0" tilt="-90"/>
      <min fovpixel="2" pan="0" tilt="-90"/>
      <max fovfisheye="360" scaletofit="1" fovstereographic="330" fov="140" pan="360" tilt="90"/>
    </view>
    <userdata nodeid="node13" datetime="2024:10:12 09:45:41" latitude="37.328506" heading="0" title="실외기실" tags="101동 901호 VR" customnodeid="" comment="" author="" info="" source="" copyright="" longitude="127.129253" description="" altitude="139.57"/>
    <hotspots smoothmovement="0" width="180" height="20" wordwrap="1">
      <label textalpha="1" borderradius="1" height="20" textcolor="0x000000" wordwrap="1" width="180" enabled="1" backgroundcolor="0xffffff" borderalpha="1" background="1" backgroundalpha="1" bordercolor="0x000000" border="1"/>
      <polystyle backgroundcolor="0x0000ff" borderalpha="1" handcursor="1" backgroundalpha="0.25098" mode="0" bordercolor="0x0000ff"/>
      <hotspot tilt="-31.77" url="{node14}" skinid="ht_node" title="현관창고" pan="-191.18" description="" target="" id="Point01"/>
    </hotspots>
    <media/>
    <transition zoomout="0" zoomin="0" blendcolor="0x000000" type="crossdissolve" zoomafterinfov="140" zoomspeed="2" blendtime="1" delay="none" enabled="1" softedge="0" zoomoutpause="1" zoomfov="40" zoomafteroutfov="40"/>
    <autorotate speed="0.020" useanimation="0" nodedelay="0.00" nodefilter="" startloaded="0" horizonfromdefview="0" noderandom="1" delay="10.00" enabled="1" returntohorizon="0.000"/>
    <animation syncanimationwithvideo="0" clipsrandom="0" animsequence="Animation01" useinautorotation="0"/>
    <control invertcontrol="1" lockedmouse="0" sensitivity="8" rubberband="0" lockedkeyboard="0" dblclickfullscreen="0" zoomcentercursor="1" contextfullscreen="1" contextprojections="0" lockedkeyboardzoom="0" invertwheel="0" speedwheel="1" contextvr="1" lockedwheel="0" simulatemass="1" hideabout="1"/>
  </panorama>
  <panorama hideabout="1" id="node4">
    <input height="2000" levelingpitch="0" width="2000" leveltilesize="510" levelbiashidpi="1.000" levelingroll="0" levelbias="0.400" overlap="1" leveltileurl="tiles/node4/cf_%c/l_%l/c_%x/tile_%y.jpg">
      <level predecode="0" width="2000" height="2000" preload="0"/>
      <level predecode="0" width="1000" height="1000" preload="0"/>
      <level predecode="1" width="500" height="500" preload="1"/>
      <preview strip="1" color="0x808080"/>
    </input>
    <view pannorth="0" fovmode="2">
      <start projection="4" fov="140.418" pan="179.115" tilt="-1.23534"/>
      <flyin projection="9" fov="170" pan="0" tilt="-90"/>
      <min fovpixel="2" pan="0" tilt="-90"/>
      <max fovfisheye="360" scaletofit="1" fovstereographic="330" fov="140" pan="360" tilt="90"/>
    </view>
    <userdata nodeid="node4" datetime="2024:10:12 09:45:11" latitude="37.328506" heading="0" title="침실1" tags="101동 901호 VR" customnodeid="" comment="" author="" info="" source="" copyright="" longitude="127.129253" description="" altitude="139.57"/>
    <hotspots smoothmovement="0" width="180" height="20" wordwrap="1">
      <label textalpha="1" borderradius="1" height="20" textcolor="0x000000" wordwrap="1" width="180" enabled="1" backgroundcolor="0xffffff" borderalpha="1" background="1" backgroundalpha="1" bordercolor="0x000000" border="1"/>
      <polystyle backgroundcolor="0x0000ff" borderalpha="1" handcursor="1" backgroundalpha="0.25098" mode="0" bordercolor="0x0000ff"/>
      <hotspot tilt="-23.85" url="{node3}" skinid="ht_node" title="파우더룸" pan="-202.79" description="" target="" id="Point01"/>
      <hotspot tilt="-19.36" url="{node7}" skinid="ht_node" title="복도1" pan="-118.9" description="" target="" id="Point02"/>
    </hotspots>
    <media/>
    <transition zoomout="0" zoomin="0" blendcolor="0x000000" type="crossdissolve" zoomafterinfov="140" zoomspeed="2" blendtime="1" delay="none" enabled="1" softedge="0" zoomoutpause="1" zoomfov="40" zoomafteroutfov="40"/>
    <autorotate speed="0.020" useanimation="0" nodedelay="0.00" nodefilter="" startloaded="0" horizonfromdefview="0" noderandom="1" delay="10.00" enabled="1" returntohorizon="0.000"/>
    <animation syncanimationwithvideo="0" clipsrandom="0" animsequence="Animation01" useinautorotation="0"/>
    <control invertcontrol="1" lockedmouse="0" sensitivity="8" rubberband="0" lockedkeyboard="0" dblclickfullscreen="0" zoomcentercursor="1" contextfullscreen="1" contextprojections="0" lockedkeyboardzoom="0" invertwheel="0" speedwheel="1" contextvr="1" lockedwheel="0" simulatemass="1" hideabout="1"/>
  </panorama>
  <panorama hideabout="1" id="node3">
    <input height="2000" levelingpitch="0" width="2000" leveltilesize="510" levelbiashidpi="1.000" levelingroll="0" levelbias="0.400" overlap="1" leveltileurl="tiles/node3/cf_%c/l_%l/c_%x/tile_%y.jpg">
      <level predecode="0" width="2000" height="2000" preload="0"/>
      <level predecode="0" width="1000" height="1000" preload="0"/>
      <level predecode="1" width="500" height="500" preload="1"/>
      <preview strip="1" color="0x808080"/>
    </input>
    <view pannorth="0" fovmode="2">
      <start projection="4" fov="100" pan="0" tilt="0"/>
      <flyin projection="9" fov="170" pan="0" tilt="-90"/>
      <min fovpixel="2" pan="0" tilt="-90"/>
      <max fovfisheye="360" scaletofit="1" fovstereographic="330" fov="140" pan="360" tilt="90"/>
    </view>
    <userdata nodeid="node3" datetime="2024:10:12 09:45:08" latitude="37.328506" heading="0" title="파우더룸" tags="101동 901호 VR" customnodeid="" comment="" author="" info="" source="" copyright="" longitude="127.129253" description="" altitude="139.57"/>
    <hotspots smoothmovement="0" width="180" height="20" wordwrap="1">
      <label textalpha="1" borderradius="1" height="20" textcolor="0x000000" wordwrap="1" width="180" enabled="1" backgroundcolor="0xffffff" borderalpha="1" background="1" backgroundalpha="1" bordercolor="0x000000" border="1"/>
      <polystyle backgroundcolor="0x0000ff" borderalpha="1" handcursor="1" backgroundalpha="0.25098" mode="0" bordercolor="0x0000ff"/>
      <hotspot tilt="-20.83" url="{node4}" skinid="ht_node" title="침실1" pan="-196.14" description="" target="" id="Point01"/>
      <hotspot tilt="-34.25" url="{node1}" skinid="ht_node" title="부부욕실" pan="-258.73" description="" target="" id="Point02"/>
      <hotspot tilt="-25.1" url="{node2}" skinid="ht_node" title="드레스룸" pan="-353.28" description="" target="" id="Point03"/>
    </hotspots>
    <media/>
    <transition zoomout="0" zoomin="0" blendcolor="0x000000" type="crossdissolve" zoomafterinfov="140" zoomspeed="2" blendtime="1" delay="none" enabled="1" softedge="0" zoomoutpause="1" zoomfov="40" zoomafteroutfov="40"/>
    <autorotate speed="0.020" useanimation="0" nodedelay="0.00" nodefilter="" startloaded="0" horizonfromdefview="0" noderandom="1" delay="10.00" enabled="1" returntohorizon="0.000"/>
    <animation syncanimationwithvideo="0" clipsrandom="0" animsequence="Animation01" useinautorotation="0"/>
    <control invertcontrol="1" lockedmouse="0" sensitivity="8" rubberband="0" lockedkeyboard="0" dblclickfullscreen="0" zoomcentercursor="1" contextfullscreen="1" contextprojections="0" lockedkeyboardzoom="0" invertwheel="0" speedwheel="1" contextvr="1" lockedwheel="0" simulatemass="1" hideabout="1"/>
  </panorama>
  <panorama hideabout="1" id="node2">
    <input height="2000" levelingpitch="0" width="2000" leveltilesize="510" levelbiashidpi="1.000" levelingroll="0" levelbias="0.400" overlap="1" leveltileurl="tiles/node2/cf_%c/l_%l/c_%x/tile_%y.jpg">
      <level predecode="0" width="2000" height="2000" preload="0"/>
      <level predecode="0" width="1000" height="1000" preload="0"/>
      <level predecode="1" width="500" height="500" preload="1"/>
      <preview strip="1" color="0x808080"/>
    </input>
    <view pannorth="0" fovmode="2">
      <start projection="4" fov="140.418" pan="179.945" tilt="-0.531458"/>
      <flyin projection="9" fov="170" pan="0" tilt="-90"/>
      <min fovpixel="2" pan="0" tilt="-90"/>
      <max fovfisheye="360" scaletofit="1" fovstereographic="330" fov="140" pan="360" tilt="90"/>
    </view>
    <userdata nodeid="node2" datetime="2024:10:12 09:45:05" latitude="37.328506" heading="0" title="드레스룸" tags="101동 901호 VR" customnodeid="" comment="" author="" info="" source="" copyright="" longitude="127.129253" description="" altitude="139.57"/>
    <hotspots smoothmovement="0" width="180" height="20" wordwrap="1">
      <label textalpha="1" borderradius="1" height="20" textcolor="0x000000" wordwrap="1" width="180" enabled="1" backgroundcolor="0xffffff" borderalpha="1" background="1" backgroundalpha="1" bordercolor="0x000000" border="1"/>
      <polystyle backgroundcolor="0x0000ff" borderalpha="1" handcursor="1" backgroundalpha="0.25098" mode="0" bordercolor="0x0000ff"/>
      <hotspot tilt="-28.91" url="{node3}" skinid="ht_node" title="파우더룸" pan="-180.42" description="" target="" id="Point01"/>
    </hotspots>
    <media/>
    <transition zoomout="0" zoomin="0" blendcolor="0x000000" type="crossdissolve" zoomafterinfov="140" zoomspeed="2" blendtime="1" delay="none" enabled="1" softedge="0" zoomoutpause="1" zoomfov="40" zoomafteroutfov="40"/>
    <autorotate speed="0.020" useanimation="0" nodedelay="0.00" nodefilter="" startloaded="0" horizonfromdefview="0" noderandom="1" delay="10.00" enabled="1" returntohorizon="0.000"/>
    <animation syncanimationwithvideo="0" clipsrandom="0" animsequence="Animation01" useinautorotation="0"/>
    <control invertcontrol="1" lockedmouse="0" sensitivity="8" rubberband="0" lockedkeyboard="0" dblclickfullscreen="0" zoomcentercursor="1" contextfullscreen="1" contextprojections="0" lockedkeyboardzoom="0" invertwheel="0" speedwheel="1" contextvr="1" lockedwheel="0" simulatemass="1" hideabout="1"/>
  </panorama>
  <panorama hideabout="1" id="node1">
    <input height="2000" levelingpitch="0" width="2000" leveltilesize="510" levelbiashidpi="1.000" levelingroll="0" levelbias="0.400" overlap="1" leveltileurl="tiles/node1/cf_%c/l_%l/c_%x/tile_%y.jpg">
      <level predecode="0" width="2000" height="2000" preload="0"/>
      <level predecode="0" width="1000" height="1000" preload="0"/>
      <level predecode="1" width="500" height="500" preload="1"/>
      <preview strip="1" color="0x808080"/>
    </input>
    <view pannorth="0" fovmode="2">
      <start projection="4" fov="140.418" pan="-92.3978" tilt="-0.111737"/>
      <flyin projection="9" fov="170" pan="0" tilt="-90"/>
      <min fovpixel="2" pan="0" tilt="-90"/>
      <max fovfisheye="360" scaletofit="1" fovstereographic="330" fov="140" pan="360" tilt="90"/>
    </view>
    <userdata nodeid="node1" datetime="2024:10:12 09:45:01" latitude="37.328506" heading="0" title="부부욕실" tags="101동 901호 VR" customnodeid="" comment="" author="" info="" source="" copyright="" longitude="127.129253" description="" altitude="139.57"/>
    <hotspots smoothmovement="0" width="180" height="20" wordwrap="1">
      <label textalpha="1" borderradius="1" height="20" textcolor="0x000000" wordwrap="1" width="180" enabled="1" backgroundcolor="0xffffff" borderalpha="1" background="1" backgroundalpha="1" bordercolor="0x000000" border="1"/>
      <polystyle backgroundcolor="0x0000ff" borderalpha="1" handcursor="1" backgroundalpha="0.25098" mode="0" bordercolor="0x0000ff"/>
      <hotspot tilt="-36.49" url="{node3}" skinid="ht_node" title="파우더룸" pan="-186.45" description="" target="" id="Point01"/>
    </hotspots>
    <media/>
    <transition zoomout="0" zoomin="0" blendcolor="0x000000" type="crossdissolve" zoomafterinfov="140" zoomspeed="2" blendtime="1" delay="none" enabled="1" softedge="0" zoomoutpause="1" zoomfov="40" zoomafteroutfov="40"/>
    <autorotate speed="0.020" useanimation="0" nodedelay="0.00" nodefilter="" startloaded="0" horizonfromdefview="0" noderandom="1" delay="10.00" enabled="1" returntohorizon="0.000"/>
    <animation syncanimationwithvideo="0" clipsrandom="0" animsequence="Animation01" useinautorotation="0"/>
    <control invertcontrol="1" lockedmouse="0" sensitivity="8" rubberband="0" lockedkeyboard="0" dblclickfullscreen="0" zoomcentercursor="1" contextfullscreen="1" contextprojections="0" lockedkeyboardzoom="0" invertwheel="0" speedwheel="1" contextvr="1" lockedwheel="0" simulatemass="1" hideabout="1"/>
  </panorama>
  <panorama hideabout="1" id="node7">
    <input height="2000" levelingpitch="0" width="2000" leveltilesize="510" levelbiashidpi="1.000" levelingroll="0" levelbias="0.400" overlap="1" leveltileurl="tiles/node7/cf_%c/l_%l/c_%x/tile_%y.jpg">
      <level predecode="0" width="2000" height="2000" preload="0"/>
      <level predecode="0" width="1000" height="1000" preload="0"/>
      <level predecode="1" width="500" height="500" preload="1"/>
      <preview strip="1" color="0x808080"/>
    </input>
    <view pannorth="0" fovmode="2">
      <start projection="4" fov="140.418" pan="173.012" tilt="-0.417527"/>
      <flyin projection="9" fov="170" pan="0" tilt="-90"/>
      <min fovpixel="2" pan="0" tilt="-90"/>
      <max fovfisheye="360" scaletofit="1" fovstereographic="330" fov="140" pan="360" tilt="90"/>
    </view>
    <userdata nodeid="node7" datetime="2024:10:12 09:45:21" latitude="37.328506" heading="0" title="복도1" tags="101동 901호 VR" customnodeid="" comment="" author="" info="" source="" copyright="" longitude="127.129253" description="" altitude="139.57"/>
    <hotspots smoothmovement="0" width="180" height="20" wordwrap="1">
      <label textalpha="1" borderradius="1" height="20" textcolor="0x000000" wordwrap="1" width="180" enabled="1" backgroundcolor="0xffffff" borderalpha="1" background="1" backgroundalpha="1" bordercolor="0x000000" border="1"/>
      <polystyle backgroundcolor="0x0000ff" borderalpha="1" handcursor="1" backgroundalpha="0.25098" mode="0" bordercolor="0x0000ff"/>
      <hotspot tilt="-13.39" url="{node6}" skinid="ht_node" title="주방" pan="-356.19" description="" target="" id="Point01"/>
      <hotspot tilt="-19.09" url="{node11}" skinid="ht_node" title="복도2" pan="-241.09" description="" target="" id="Point02"/>
      <hotspot tilt="-17.74" url="{node8}" skinid="ht_node" title="거실" pan="-187.61" description="" target="" id="Point03"/>
      <hotspot tilt="-17.68" url="{node4}" skinid="ht_node" title="침실1" pan="-126.95" description="" target="" id="Point04"/>
    </hotspots>
    <media/>
    <transition zoomout="0" zoomin="0" blendcolor="0x000000" type="crossdissolve" zoomafterinfov="140" zoomspeed="2" blendtime="1" delay="none" enabled="1" softedge="0" zoomoutpause="1" zoomfov="40" zoomafteroutfov="40"/>
    <autorotate speed="0.020" useanimation="0" nodedelay="0.00" nodefilter="" startloaded="0" horizonfromdefview="0" noderandom="1" delay="10.00" enabled="1" returntohorizon="0.000"/>
    <animation syncanimationwithvideo="0" clipsrandom="0" animsequence="Animation01" useinautorotation="0"/>
    <control invertcontrol="1" lockedmouse="0" sensitivity="8" rubberband="0" lockedkeyboard="0" dblclickfullscreen="0" zoomcentercursor="1" contextfullscreen="1" contextprojections="0" lockedkeyboardzoom="0" invertwheel="0" speedwheel="1" contextvr="1" lockedwheel="0" simulatemass="1" hideabout="1"/>
  </panorama>
  <panorama hideabout="1" id="node8">
    <input height="2000" levelingpitch="0" width="2000" leveltilesize="510" levelbiashidpi="1.000" levelingroll="0" levelbias="0.400" overlap="1" leveltileurl="tiles/node8/cf_%c/l_%l/c_%x/tile_%y.jpg">
      <level predecode="0" width="2000" height="2000" preload="0"/>
      <level predecode="0" width="1000" height="1000" preload="0"/>
      <level predecode="1" width="500" height="500" preload="1"/>
      <preview strip="1" color="0x808080"/>
    </input>
    <view pannorth="0" fovmode="2">
      <start projection="4" fov="140.418" pan="-2.63104" tilt="-1.98863"/>
      <flyin projection="9" fov="170" pan="0" tilt="-90"/>
      <min fovpixel="2" pan="0" tilt="-90"/>
      <max fovfisheye="360" scaletofit="1" fovstereographic="330" fov="140" pan="360" tilt="90"/>
    </view>
    <userdata nodeid="node8" datetime="2024:10:12 09:45:24" latitude="37.328506" heading="0" title="거실" tags="101동 901호 VR" customnodeid="" comment="" author="" info="" source="" copyright="" longitude="127.129253" description="" altitude="139.57"/>
    <hotspots smoothmovement="0" width="180" height="20" wordwrap="1">
      <label textalpha="1" borderradius="1" height="20" textcolor="0x000000" wordwrap="1" width="180" enabled="1" backgroundcolor="0xffffff" borderalpha="1" background="1" backgroundalpha="1" bordercolor="0x000000" border="1"/>
      <polystyle backgroundcolor="0x0000ff" borderalpha="1" handcursor="1" backgroundalpha="0.25098" mode="0" bordercolor="0x0000ff"/>
      <hotspot tilt="-20.75" url="{node7}" skinid="ht_node" title="복도1" pan="-193.09" description="" target="" id="Point01"/>
      <hotspot tilt="-21.16" url="{node11}" skinid="ht_node" title="복도2" pan="-128.3" description="" target="" id="Point02"/>
      <hotspot tilt="-17.98" url="{node4}" skinid="ht_node" title="침실1" pan="-235.96" description="" target="" id="Point03"/>
    </hotspots>
    <media/>
    <transition zoomout="0" zoomin="0" blendcolor="0x000000" type="crossdissolve" zoomafterinfov="140" zoomspeed="2" blendtime="1" delay="none" enabled="1" softedge="0" zoomoutpause="1" zoomfov="40" zoomafteroutfov="40"/>
    <autorotate speed="0.020" useanimation="0" nodedelay="0.00" nodefilter="" startloaded="0" horizonfromdefview="0" noderandom="1" delay="10.00" enabled="1" returntohorizon="0.000"/>
    <animation syncanimationwithvideo="0" clipsrandom="0" animsequence="Animation01" useinautorotation="0"/>
    <control invertcontrol="1" lockedmouse="0" sensitivity="8" rubberband="0" lockedkeyboard="0" dblclickfullscreen="0" zoomcentercursor="1" contextfullscreen="1" contextprojections="0" lockedkeyboardzoom="0" invertwheel="0" speedwheel="1" contextvr="1" lockedwheel="0" simulatemass="1" hideabout="1"/>
  </panorama>
  <panorama hideabout="1" id="node6">
    <input height="2000" levelingpitch="0" width="2000" leveltilesize="510" levelbiashidpi="1.000" levelingroll="0" levelbias="0.400" overlap="1" leveltileurl="tiles/node6/cf_%c/l_%l/c_%x/tile_%y.jpg">
      <level predecode="0" width="2000" height="2000" preload="0"/>
      <level predecode="0" width="1000" height="1000" preload="0"/>
      <level predecode="1" width="500" height="500" preload="1"/>
      <preview strip="1" color="0x808080"/>
    </input>
    <view pannorth="0" fovmode="2">
      <start projection="4" fov="140.418" pan="1.20227" tilt="-1.9779"/>
      <flyin projection="9" fov="170" pan="0" tilt="-90"/>
      <min fovpixel="2" pan="0" tilt="-90"/>
      <max fovfisheye="360" scaletofit="1" fovstereographic="330" fov="140" pan="360" tilt="90"/>
    </view>
    <userdata nodeid="node6" datetime="2024:10:12 09:45:18" latitude="37.328506" heading="0" title="주방" tags="101동 901호 VR" customnodeid="" comment="" author="" info="" source="" copyright="" longitude="127.129253" description="" altitude="139.57"/>
    <hotspots smoothmovement="0" width="180" height="20" wordwrap="1">
      <label textalpha="1" borderradius="1" height="20" textcolor="0x000000" wordwrap="1" width="180" enabled="1" backgroundcolor="0xffffff" borderalpha="1" background="1" backgroundalpha="1" bordercolor="0x000000" border="1"/>
      <polystyle backgroundcolor="0x0000ff" borderalpha="1" handcursor="1" backgroundalpha="0.25098" mode="0" bordercolor="0x0000ff"/>
      <hotspot tilt="-18.48" url="{node7}" skinid="ht_node" title="복도1" pan="-180.45" description="" target="" id="Point01"/>
      <hotspot tilt="-25.95" url="{node5}" skinid="ht_node" title="다용도실" pan="-90.49" description="" target="" id="Point02"/>
    </hotspots>
    <media/>
    <transition zoomout="0" zoomin="0" blendcolor="0x000000" type="crossdissolve" zoomafterinfov="140" zoomspeed="2" blendtime="1" delay="none" enabled="1" softedge="0" zoomoutpause="1" zoomfov="40" zoomafteroutfov="40"/>
    <autorotate speed="0.020" useanimation="0" nodedelay="0.00" nodefilter="" startloaded="0" horizonfromdefview="0" noderandom="1" delay="10.00" enabled="1" returntohorizon="0.000"/>
    <animation syncanimationwithvideo="0" clipsrandom="0" animsequence="Animation01" useinautorotation="0"/>
    <control invertcontrol="1" lockedmouse="0" sensitivity="8" rubberband="0" lockedkeyboard="0" dblclickfullscreen="0" zoomcentercursor="1" contextfullscreen="1" contextprojections="0" lockedkeyboardzoom="0" invertwheel="0" speedwheel="1" contextvr="1" lockedwheel="0" simulatemass="1" hideabout="1"/>
  </panorama>
  <panorama hideabout="1" id="node5">
    <input height="2000" levelingpitch="0" width="2000" leveltilesize="510" levelbiashidpi="1.000" levelingroll="0" levelbias="0.400" overlap="1" leveltileurl="tiles/node5/cf_%c/l_%l/c_%x/tile_%y.jpg">
      <level predecode="0" width="2000" height="2000" preload="0"/>
      <level predecode="0" width="1000" height="1000" preload="0"/>
      <level predecode="1" width="500" height="500" preload="1"/>
      <preview strip="1" color="0x808080"/>
    </input>
    <view pannorth="0" fovmode="2">
      <start projection="4" fov="140.418" pan="1.34814" tilt="-1.9779"/>
      <flyin projection="9" fov="170" pan="0" tilt="-90"/>
      <min fovpixel="2" pan="0" tilt="-90"/>
      <max fovfisheye="360" scaletofit="1" fovstereographic="330" fov="140" pan="360" tilt="90"/>
    </view>
    <userdata nodeid="node5" datetime="2024:10:12 09:45:14" latitude="37.328506" heading="0" title="다용도실" tags="101동 901호 VR" customnodeid="" comment="" author="" info="" source="" copyright="" longitude="127.129253" description="" altitude="139.57"/>
    <hotspots smoothmovement="0" width="180" height="20" wordwrap="1">
      <label textalpha="1" borderradius="1" height="20" textcolor="0x000000" wordwrap="1" width="180" enabled="1" backgroundcolor="0xffffff" borderalpha="1" background="1" backgroundalpha="1" bordercolor="0x000000" border="1"/>
      <polystyle backgroundcolor="0x0000ff" borderalpha="1" handcursor="1" backgroundalpha="0.25098" mode="0" bordercolor="0x0000ff"/>
      <hotspot tilt="-25.2" url="{node6}" skinid="ht_node" title="주방" pan="-269.36" description="" target="" id="Point01"/>
    </hotspots>
    <media/>
    <transition zoomout="0" zoomin="0" blendcolor="0x000000" type="crossdissolve" zoomafterinfov="140" zoomspeed="2" blendtime="1" delay="none" enabled="1" softedge="0" zoomoutpause="1" zoomfov="40" zoomafteroutfov="40"/>
    <autorotate speed="0.020" useanimation="0" nodedelay="0.00" nodefilter="" startloaded="0" horizonfromdefview="0" noderandom="1" delay="10.00" enabled="1" returntohorizon="0.000"/>
    <animation syncanimationwithvideo="0" clipsrandom="0" animsequence="Animation01" useinautorotation="0"/>
    <control invertcontrol="1" lockedmouse="0" sensitivity="8" rubberband="0" lockedkeyboard="0" dblclickfullscreen="0" zoomcentercursor="1" contextfullscreen="1" contextprojections="0" lockedkeyboardzoom="0" invertwheel="0" speedwheel="1" contextvr="1" lockedwheel="0" simulatemass="1" hideabout="1"/>
  </panorama>
  <panorama hideabout="1" id="node11">
    <input height="2000" levelingpitch="0" width="2000" leveltilesize="510" levelbiashidpi="1.000" levelingroll="0" levelbias="0.400" overlap="1" leveltileurl="tiles/node11/cf_%c/l_%l/c_%x/tile_%y.jpg">
      <level predecode="0" width="2000" height="2000" preload="0"/>
      <level predecode="0" width="1000" height="1000" preload="0"/>
      <level predecode="1" width="500" height="500" preload="1"/>
      <preview strip="1" color="0x808080"/>
    </input>
    <view pannorth="0" fovmode="2">
      <start projection="4" fov="140.418" pan="1.34814" tilt="-1.9779"/>
      <flyin projection="9" fov="170" pan="0" tilt="-90"/>
      <min fovpixel="2" pan="0" tilt="-90"/>
      <max fovfisheye="360" scaletofit="1" fovstereographic="330" fov="140" pan="360" tilt="90"/>
    </view>
    <userdata nodeid="node11" datetime="2024:10:12 09:45:35" latitude="37.328506" heading="0" title="복도2" tags="101동 901호 VR" customnodeid="" comment="" author="" info="" source="" copyright="" longitude="127.129253" description="" altitude="139.57"/>
    <hotspots smoothmovement="0" width="180" height="20" wordwrap="1">
      <label textalpha="1" borderradius="1" height="20" textcolor="0x000000" wordwrap="1" width="180" enabled="1" backgroundcolor="0xffffff" borderalpha="1" background="1" backgroundalpha="1" bordercolor="0x000000" border="1"/>
      <polystyle backgroundcolor="0x0000ff" borderalpha="1" handcursor="1" backgroundalpha="0.25098" mode="0" bordercolor="0x0000ff"/>
      <hotspot tilt="-8.72" url="{node12}" skinid="ht_node" title="공용욕실" pan="-180.44" description="" target="" id="Point01"/>
      <hotspot tilt="-21.92" url="{node10}" skinid="ht_node" title="침실3" pan="-163.15" description="" target="" id="Point02"/>
      <hotspot tilt="-21.25" url="{node15}" skinid="ht_node" title="현관" pan="-212.85" description="" target="" id="Point03"/>
      <hotspot tilt="-17.44" url="{node7}" skinid="ht_node" title="복도1" pan="-7.44" description="" target="" id="Point04"/>
      <hotspot tilt="-25.56" url="{node9}" skinid="ht_node" title="침실2" pan="-44.73" description="" target="" id="Point05"/>
    </hotspots>
    <media/>
    <transition zoomout="0" zoomin="0" blendcolor="0x000000" type="crossdissolve" zoomafterinfov="140" zoomspeed="2" blendtime="1" delay="none" enabled="1" softedge="0" zoomoutpause="1" zoomfov="40" zoomafteroutfov="40"/>
    <autorotate speed="0.020" useanimation="0" nodedelay="0.00" nodefilter="" startloaded="0" horizonfromdefview="0" noderandom="1" delay="10.00" enabled="1" returntohorizon="0.000"/>
    <animation syncanimationwithvideo="0" clipsrandom="0" animsequence="Animation01" useinautorotation="0"/>
    <control invertcontrol="1" lockedmouse="0" sensitivity="8" rubberband="0" lockedkeyboard="0" dblclickfullscreen="0" zoomcentercursor="1" contextfullscreen="1" contextprojections="0" lockedkeyboardzoom="0" invertwheel="0" speedwheel="1" contextvr="1" lockedwheel="0" simulatemass="1" hideabout="1"/>
  </panorama>
  <panorama hideabout="1" id="node9">
    <input height="2000" levelingpitch="0" width="2000" leveltilesize="510" levelbiashidpi="1.000" levelingroll="0" levelbias="0.400" overlap="1" leveltileurl="tiles/node9/cf_%c/l_%l/c_%x/tile_%y.jpg">
      <level predecode="0" width="2000" height="2000" preload="0"/>
      <level predecode="0" width="1000" height="1000" preload="0"/>
      <level predecode="1" width="500" height="500" preload="1"/>
      <preview strip="1" color="0x808080"/>
    </input>
    <view pannorth="0" fovmode="2">
      <start projection="4" fov="140.418" pan="-2.11579" tilt="-2.09901"/>
      <flyin projection="9" fov="170" pan="0" tilt="-90"/>
      <min fovpixel="2" pan="0" tilt="-90"/>
      <max fovfisheye="360" scaletofit="1" fovstereographic="330" fov="140" pan="360" tilt="90"/>
    </view>
    <userdata nodeid="node9" datetime="2024:10:12 09:45:27" latitude="37.328506" heading="0" title="침실2" tags="101동 901호 VR" customnodeid="" comment="" author="" info="" source="" copyright="" longitude="127.129253" description="" altitude="139.57"/>
    <hotspots smoothmovement="0" width="180" height="20" wordwrap="1">
      <label textalpha="1" borderradius="1" height="20" textcolor="0x000000" wordwrap="1" width="180" enabled="1" backgroundcolor="0xffffff" borderalpha="1" background="1" backgroundalpha="1" bordercolor="0x000000" border="1"/>
      <polystyle backgroundcolor="0x0000ff" borderalpha="1" handcursor="1" backgroundalpha="0.25098" mode="0" bordercolor="0x0000ff"/>
      <hotspot tilt="-24.79" url="{node11}" skinid="ht_node" title="복도2" pan="-206.32" description="" target="" id="Point01"/>
    </hotspots>
    <media/>
    <transition zoomout="0" zoomin="0" blendcolor="0x000000" type="crossdissolve" zoomafterinfov="140" zoomspeed="2" blendtime="1" delay="none" enabled="1" softedge="0" zoomoutpause="1" zoomfov="40" zoomafteroutfov="40"/>
    <autorotate speed="0.020" useanimation="0" nodedelay="0.00" nodefilter="" startloaded="0" horizonfromdefview="0" noderandom="1" delay="10.00" enabled="1" returntohorizon="0.000"/>
    <animation syncanimationwithvideo="0" clipsrandom="0" animsequence="Animation01" useinautorotation="0"/>
    <control invertcontrol="1" lockedmouse="0" sensitivity="8" rubberband="0" lockedkeyboard="0" dblclickfullscreen="0" zoomcentercursor="1" contextfullscreen="1" contextprojections="0" lockedkeyboardzoom="0" invertwheel="0" speedwheel="1" contextvr="1" lockedwheel="0" simulatemass="1" hideabout="1"/>
  </panorama>
  <panorama hideabout="1" id="node10">
    <input height="2000" levelingpitch="0" width="2000" leveltilesize="510" levelbiashidpi="1.000" levelingroll="0" levelbias="0.400" overlap="1" leveltileurl="tiles/node10/cf_%c/l_%l/c_%x/tile_%y.jpg">
      <level predecode="0" width="2000" height="2000" preload="0"/>
      <level predecode="0" width="1000" height="1000" preload="0"/>
      <level predecode="1" width="500" height="500" preload="1"/>
      <preview strip="1" color="0x808080"/>
    </input>
    <view pannorth="0" fovmode="2">
      <start projection="4" fov="140.418" pan="2.08899" tilt="-1.84278"/>
      <flyin projection="9" fov="170" pan="0" tilt="-90"/>
      <min fovpixel="2" pan="0" tilt="-90"/>
      <max fovfisheye="360" scaletofit="1" fovstereographic="330" fov="140" pan="360" tilt="90"/>
    </view>
    <userdata nodeid="node10" datetime="2024:10:12 09:45:31" latitude="37.328506" heading="0" title="침실3" tags="101동 901호 VR" customnodeid="" comment="" author="" info="" source="" copyright="" longitude="127.129253" description="" altitude="139.57"/>
    <hotspots smoothmovement="0" width="180" height="20" wordwrap="1">
      <label textalpha="1" borderradius="1" height="20" textcolor="0x000000" wordwrap="1" width="180" enabled="1" backgroundcolor="0xffffff" borderalpha="1" background="1" backgroundalpha="1" bordercolor="0x000000" border="1"/>
      <polystyle backgroundcolor="0x0000ff" borderalpha="1" handcursor="1" backgroundalpha="0.25098" mode="0" bordercolor="0x0000ff"/>
      <hotspot tilt="-23.35" url="{node11}" skinid="ht_node" title="복도2" pan="-206.59" description="" target="" id="Point01"/>
    </hotspots>
    <media/>
    <transition zoomout="0" zoomin="0" blendcolor="0x000000" type="crossdissolve" zoomafterinfov="140" zoomspeed="2" blendtime="1" delay="none" enabled="1" softedge="0" zoomoutpause="1" zoomfov="40" zoomafteroutfov="40"/>
    <autorotate speed="0.020" useanimation="0" nodedelay="0.00" nodefilter="" startloaded="0" horizonfromdefview="0" noderandom="1" delay="10.00" enabled="1" returntohorizon="0.000"/>
    <animation syncanimationwithvideo="0" clipsrandom="0" animsequence="Animation01" useinautorotation="0"/>
    <control invertcontrol="1" lockedmouse="0" sensitivity="8" rubberband="0" lockedkeyboard="0" dblclickfullscreen="0" zoomcentercursor="1" contextfullscreen="1" contextprojections="0" lockedkeyboardzoom="0" invertwheel="0" speedwheel="1" contextvr="1" lockedwheel="0" simulatemass="1" hideabout="1"/>
  </panorama>
  <panorama hideabout="1" id="node12">
    <input height="2000" levelingpitch="0" width="2000" leveltilesize="510" levelbiashidpi="1.000" levelingroll="0" levelbias="0.400" overlap="1" leveltileurl="tiles/node12/cf_%c/l_%l/c_%x/tile_%y.jpg">
      <level predecode="0" width="2000" height="2000" preload="0"/>
      <level predecode="0" width="1000" height="1000" preload="0"/>
      <level predecode="1" width="500" height="500" preload="1"/>
      <preview strip="1" color="0x808080"/>
    </input>
    <view pannorth="0" fovmode="2">
      <start projection="4" fov="140.418" pan="-0.773177" tilt="-2.42324"/>
      <flyin projection="9" fov="170" pan="0" tilt="-90"/>
      <min fovpixel="2" pan="0" tilt="-90"/>
      <max fovfisheye="360" scaletofit="1" fovstereographic="330" fov="140" pan="360" tilt="90"/>
    </view>
    <userdata nodeid="node12" datetime="2024:10:12 09:45:38" latitude="37.328506" heading="0" title="공용욕실" tags="101동 901호 VR" customnodeid="" comment="" author="" info="" source="" copyright="" longitude="127.129253" description="" altitude="139.57"/>
    <hotspots smoothmovement="0" width="180" height="20" wordwrap="1">
      <label textalpha="1" borderradius="1" height="20" textcolor="0x000000" wordwrap="1" width="180" enabled="1" backgroundcolor="0xffffff" borderalpha="1" background="1" backgroundalpha="1" bordercolor="0x000000" border="1"/>
      <polystyle backgroundcolor="0x0000ff" borderalpha="1" handcursor="1" backgroundalpha="0.25098" mode="0" bordercolor="0x0000ff"/>
      <hotspot tilt="-30.75" url="{node11}" skinid="ht_node" title="복도2" pan="-207.88" description="" target="" id="Point01"/>
    </hotspots>
    <media/>
    <transition zoomout="0" zoomin="0" blendcolor="0x000000" type="crossdissolve" zoomafterinfov="140" zoomspeed="2" blendtime="1" delay="none" enabled="1" softedge="0" zoomoutpause="1" zoomfov="40" zoomafteroutfov="40"/>
    <autorotate speed="0.020" useanimation="0" nodedelay="0.00" nodefilter="" startloaded="0" horizonfromdefview="0" noderandom="1" delay="10.00" enabled="1" returntohorizon="0.000"/>
    <animation syncanimationwithvideo="0" clipsrandom="0" animsequence="Animation01" useinautorotation="0"/>
    <control invertcontrol="1" lockedmouse="0" sensitivity="8" rubberband="0" lockedkeyboard="0" dblclickfullscreen="0" zoomcentercursor="1" contextfullscreen="1" contextprojections="0" lockedkeyboardzoom="0" invertwheel="0" speedwheel="1" contextvr="1" lockedwheel="0" simulatemass="1" hideabout="1"/>
  </panorama>
  <masternode>
    <userdata copyright="" title="이편한세상 죽전 프리미어포레" tags="" comment="" description="101동 901호" author=""/>
    <animationsequences>
      <sequence title="Animation01"/>
    </animationsequences>
  </masternode>
</tour>
